clrppy/__init__.py
clrppy-0.0.1.dist-info/METADATA
clrppy-0.0.1.dist-info/WHEEL
clrppy-0.0.1.dist-info/top_level.txt
clrppy-0.0.1.dist-info/RECORD
