Metadata-Version: 2.1
Name: clrppy
Version: 0.0.1
Summary: More Simple Printing With Color
Home-page: https://github.com/s0rmayz/clrppy
Author: s0rmayz
Author-email: 2430545310@qq.com
Project-URL: Github Page, https://github.com/s0rmayz/clrppy/issues
Classifier: Programming Language :: Python :: 3
Classifier: License :: OSI Approved :: MIT License
Classifier: Operating System :: OS Independent
Requires-Python: >=3.6
